rolang/__init__.py
rolang/interpreter.py
rolang-0.1.dist-info/licenses/LICENSE
rolang-0.1.dist-info/METADATA
rolang-0.1.dist-info/WHEEL
rolang-0.1.dist-info/entry_points.txt
rolang-0.1.dist-info/top_level.txt
rolang-0.1.dist-info/RECORD
