Metadata-Version: 2.4
Name: rolang
Version: 0.1
Summary: A simple custom programming language interpreter
Author: Rohan
Author-email: ronk5811@gmail.com
Requires-Python: >=3.6
License-File: LICENSE
Dynamic: author
Dynamic: author-email
Dynamic: license-file
Dynamic: requires-python
Dynamic: summary
